{
  "version": "4.5.4",
  "flags": {},
  "shapes": [
    {
      "label": "This is the loss function for l1 regularization otherwise known as lasso objective",
      "points": [
        [
          262.46153846153845,
          189.6153846153846
        ],
        [
          742.8461538461538,
          288.46153846153845
        ]
      ],
      "group_id": null,
      "shape_type": "rectangle",
      "flags": {}
    }
  ],
  "imagePath": "slides06-05.jpg",
  "imageData": null,
  "imageHeight": 756,
  "imageWidth": 1008
}